ckb/__init__.py
ckb/block.py
ckb/cbmt.py
ckb/hash.py
ckb/header.py
ckb/hex_coder.py
ckb/molecule.py
ckb/rpc.py
ckb/test_block.py
ckb/test_cbmt.py
ckb/test_header.py
ckb/test_transaction.py
ckb/transaction.py
ckb/types.py
ckb/uncle_block.py
ckb/version.py
ckb-0.6.0.dist-info/METADATA
ckb-0.6.0.dist-info/WHEEL
ckb-0.6.0.dist-info/top_level.txt
ckb-0.6.0.dist-info/RECORD
