Metadata-Version: 2.1
Name: ckb
Version: 0.6.0
Summary: Nervos CKB SDK
Home-page: https://github.com/doitian/ckb-sdk-python
Author: ian
Author-email: ian@nervos.org
License: MIT
Classifier: Development Status :: 2 - Pre-Alpha
Classifier: Environment :: Console
Requires-Dist: jsonrpcclient
Requires-Dist: requests
Requires-Dist: typing-extensions
